README.rst
setup.py
django_pindb.egg-info/PKG-INFO
django_pindb.egg-info/SOURCES.txt
django_pindb.egg-info/dependency_links.txt
django_pindb.egg-info/requires.txt
django_pindb.egg-info/top_level.txt
pindb/__init__.py
pindb/exceptions.py
pindb/middleware.py
pindb/models.py
pindb/tests.py
test_project/__init__.py
test_project/router.py
test_project/settings.py
test_project/test_runner.py
test_project/urls.py
test_project/test_app/__init__.py
test_project/test_app/models.py
test_project/test_app/urls.py
test_project/test_app/views.py