Metadata-Version: 1.1
Name: django-pindb
Version: 0.1.12
Summary: Manages master/replica pinning for django
Home-page: https://github.com/votizen/django-pindb
Author: Jeremy Dunck
Author-email: jdunck@votizen.com
License: MIT
Keywords: django,multidb,router
Platform: any
Classifier: Programming Language :: Python
Classifier: License :: OSI Approved :: MIT License
Classifier: Operating System :: OS Independent
Classifier: Development Status :: 3 - Alpha
Classifier: Environment :: Web Environment
Classifier: Framework :: Django
Classifier: Intended Audience :: Developers
Classifier: Topic :: Software Development :: Libraries :: Python Modules
